find_and_replace
tests
