Metadata-Version: 2.1
Name: find-and-replace-template-commit-check
Version: 0.8.0
Summary: Finds strings in files and replaces them with other strings.
Home-page: https://example.com
Author: Andre Ouellet
Author-email: me@here.com
License: MIT
